easycim/__init__.py
easycim/data_iterator.py
easycim/get_all_data.py
easycim/inverter_data.py
easycim/line_geometry_data.py
easycim/line_impedance_data.py
easycim/load_data.py
easycim/reduced_data_profile.py
easycim/split_phase_transformer.py
easycim/swing_bus_data.py
easycim/three_phase_transformer_data.py
easycim-0.1.1a0.dist-info/LICENSE
easycim-0.1.1a0.dist-info/METADATA
easycim-0.1.1a0.dist-info/WHEEL
easycim-0.1.1a0.dist-info/RECORD
