Metadata-Version: 2.1
Name: easycim
Version: 0.1.1a0
Summary: Simplified Dictionaries of CIM data
Author: A. Anderson
Author-email: 19935503+AAndersn@users.noreply.github.com
Requires-Python: >=3.8.1,<4.0
Classifier: Programming Language :: Python :: 3
Classifier: Programming Language :: Python :: 3.9
Classifier: Programming Language :: Python :: 3.10
Classifier: Programming Language :: Python :: 3.11
Classifier: Programming Language :: Python :: 3.12
Requires-Dist: cim-graph (>=0.1.2a0,<0.2.0)
